depro/__init__.py
depro/data.py
depro/depro.py
depro/_utils/__init__.py
depro/_utils/assistant.py
depro/_utils/converter.py
depro/_utils/loader.py
depro/_utils/normalizer.py
depro/_utils/path_handler.py
depro/_utils/statistics.py
depro/decomposer/__init__.py
depro/decomposer/decomposer.py
depro/decomposer/ex_decomposer.py
depro/decomposer/initializer/__init__.py
depro/decomposer/initializer/initializer.py
depro/decomposer/initializer/principal_component.py
depro/decomposer/rotator/__init__.py
depro/decomposer/rotator/promax.py
depro/decomposer/rotator/rotator.py
depro/decomposer/rotator/varimax.py
depro/estimator/__init__.py
depro/estimator/_est_plot.py
depro/estimator/accumulation.py
depro/estimator/estimator.py
depro/estimator/mapc.py
depro/estimator/parallel.py
depro/estimator/smc.py
depro/plot/__init__.py
depro/plot/plot.py
depro/preprocess/__init__.py
depro/preprocess/deg.py
depro/preprocess/mirror.py
depro/preprocess/preprocessor.py
depro/preprocess/smir_grub.py
depro/preprocess/sphere.py
depro-0.0.12.dist-info/LICENSE.txt
depro-0.0.12.dist-info/METADATA
depro-0.0.12.dist-info/WHEEL
depro-0.0.12.dist-info/top_level.txt
depro-0.0.12.dist-info/RECORD
